fnutil/__init__.py
fnutil/base.py
fnutil/expr.py
fnutil/expr.pyi
fnutil/if_.py
fnutil/if_.pyi
fnutil/iterator.py
fnutil/match.py
fnutil/match.pyi
fnutil/py.typed
fnutil-0.0.2.dist-info/licenses/LICENSE
fnutil-0.0.2.dist-info/METADATA
fnutil-0.0.2.dist-info/WHEEL
fnutil-0.0.2.dist-info/top_level.txt
fnutil-0.0.2.dist-info/RECORD
