Metadata-Version: 2.4
Name: fnutil
Version: 0.0.2
Summary: Lightweight functional-style helpers for Python 3.13+
Author-email: Luke Scherrer <lscherrer2@gmail.com>
License-Expression: MIT
Project-URL: Homepage, https://github.com/lscherrer2/fnutil
Project-URL: Issues, https://github.com/lscherrer2/fnutil/issues
Classifier: Programming Language :: Python :: 3
Classifier: Operating System :: OS Independent
Requires-Python: >=3.13
License-File: LICENSE
Requires-Dist: typeguard>=4.4.4
Dynamic: license-file
